inmanta_plugins/drupal/__init__.py
inmanta_plugins/drupal/setup.cfg
inmanta_plugins/drupal/files/is_drupal_installed.sh
inmanta_plugins/drupal/model/_init.cf
inmanta_plugins/drupal/templates/settings.php.tmpl
inmanta_module_drupal-0.7.9.dist-info/METADATA
inmanta_module_drupal-0.7.9.dist-info/WHEEL
inmanta_module_drupal-0.7.9.dist-info/top_level.txt
inmanta_module_drupal-0.7.9.dist-info/RECORD
