Metadata-Version: 2.1
Name: inmanta-module-drupal
Version: 0.7.9
License: Apache 2.0
Requires-Dist: inmanta-module-apache
Requires-Dist: inmanta-module-exec
Requires-Dist: inmanta-module-mysql (>=0.3.1)
Requires-Dist: inmanta-module-php
Requires-Dist: inmanta-module-std
Requires-Dist: inmanta-module-web
